atomic_assembler/__init__.py
atomic_assembler/app.py
atomic_assembler/color_utils.py
atomic_assembler/constants.py
atomic_assembler/main.py
atomic_assembler/utils.py
atomic_assembler/screens/atomic_tool_explorer.py
atomic_assembler/screens/file_explorer.py
atomic_assembler/screens/main_menu.py
atomic_assembler/screens/tool_info_screen.py
atomic_assembler/widgets/confirmation_modal.py
atomic_assembler/widgets/generic_list.py
atomic_assembler/widgets/gradient_title.py
atomic_assembler/widgets/icon_selection_list.py
atomic_assembler/widgets/menu.py
atomic_assembler/widgets/new_item_input.py
atomic_assembler/widgets/tool_info_display.py
atomic_assembler-0.1.2.dist-info/METADATA
atomic_assembler-0.1.2.dist-info/WHEEL
atomic_assembler-0.1.2.dist-info/entry_points.txt
atomic_assembler-0.1.2.dist-info/RECORD
