Metadata-Version: 2.3
Name: atomic-assembler
Version: 0.1.2
Summary: Add your description here
Requires-Python: >=3.12
Requires-Dist: gitpython<3.2.0,>=3.1.43
Requires-Dist: pyfiglet<2.0.0,>=1.0.2
Requires-Dist: pyyaml<7.0.0,>=6.0.2
Requires-Dist: rich<14.0.0,>=13.7.1
Requires-Dist: textual<0.78.0,>=0.77.0
